pycustomcfn/__init__.py
pycustomcfn/functions.py
pycustomcfn-0.1.3.dist-info/LICENSE
pycustomcfn-0.1.3.dist-info/WHEEL
pycustomcfn-0.1.3.dist-info/METADATA
pycustomcfn-0.1.3.dist-info/RECORD
